decopts.py
decopts-1.0.2.dist-info/DESCRIPTION.rst
decopts-1.0.2.dist-info/METADATA
decopts-1.0.2.dist-info/RECORD
decopts-1.0.2.dist-info/WHEEL
decopts-1.0.2.dist-info/metadata.json
decopts-1.0.2.dist-info/top_level.txt
