Metadata-Version: 2.0
Name: decopts
Version: 1.0.2
Summary: Use decorators for dealing with argparse
Home-page: https://github.com/Eeems/decopts
Author: Nathaniel van Diepen
Author-email: eeems13@gmail.com
License: MIT
Keywords: optparse argparse
Platform: UNKNOWN
Classifier: Development Status :: 3 - Alpha
Classifier: Environment :: Console
Classifier: Intended Audience :: Developers
Classifier: License :: OSI Approved :: MIT License
Classifier: Programming Language :: Python :: 2
Classifier: Programming Language :: Python :: 2.7
Classifier: Topic :: Software Development :: Libraries
Classifier: Topic :: Terminals
Provides-Extra: dev
Requires-Dist: pypandoc; extra == 'dev'
